fsdiffnet/MyClass.py
fsdiffnet/__init__.py
fsdiffnet/fit.py
fsdiffnet/generate_data.py
fsdiffnet/infer.py
fsdiffnet/model_architecture.py
fsdiffnet/utils.py
fsdiffnet/models/ABIDE.pt
fsdiffnet/models/BRCA.pt
fsdiffnet/models/default.pt
fsdiffnet/models/large.pt
"fsdiffnet/models/model_BA_diff_hub_mixed_p[20, 30, 40, 50, 60, 70, 80]n70_s[0.1, 0.3]_dr[0.3, 0.7]_r10_N200_float_DT_DS_nfFSDiffNet.pt"
fsdiffnet/models/normal.pt
fsdiffnet/models/single-condition_model.pt
fsdiffnet-0.12.dist-info/LICENSE
fsdiffnet-0.12.dist-info/METADATA
fsdiffnet-0.12.dist-info/WHEEL
fsdiffnet-0.12.dist-info/top_level.txt
fsdiffnet-0.12.dist-info/RECORD
