Metadata-Version: 2.1
Name: fsdiffnet
Version: 0.12
Author: Jiacheng Leng
Author-email: jcleng@zhejianglab.com
License-File: LICENSE
Requires-Dist: matplotlib
Requires-Dist: nilearn
Requires-Dist: networkx
Requires-Dist: numpy
Requires-Dist: pandas
Requires-Dist: progressbar2
Requires-Dist: rpy2
Requires-Dist: scikit-learn
Requires-Dist: scipy
Requires-Dist: seaborn
Requires-Dist: torch
Requires-Dist: torchaudio
Requires-Dist: torchvision
Requires-Dist: tqdm
Requires-Dist: wandb
